Metadata-Version: 2.1
Name: motornet
Version: 0.2.0
Summary: A PyTorch-powered python toolbox to train deep neural networks to perform motor tasks.
Author-email: Olivier Codol <codol.olivier@gmail.com>
Project-URL: Homepage, https://oliviercodol.github.io/MotorNet/build/html/index.html
Project-URL: Github, https://github.com/OlivierCodol/MotorNet
Keywords: motornet,pytorch
Classifier: Programming Language :: Python :: 3
Classifier: License :: OSI Approved :: GNU General Public License v3 (GPLv3)
Classifier: Operating System :: OS Independent
Requires-Python: >=3.10
License-File: LICENSE
Requires-Dist: numpy
Requires-Dist: torch
Requires-Dist: gymnasium
Requires-Dist: matplotlib
